{
    "@description": "${template.description}",
    "@group": "SecondaryContent",
    "ecr:createDate": "2016-12-07T09:49:28.163Z",
    "@thumbnailUrl": "thumbnail.jpg",
    "ecr:type": "template",
    "editorPanel": {
        "editor": "editors/DefaultEditorPanel",
        "children": []
    },
    "typeInfo": {"displayNamePropertyAlias": {"@propertyType": "String"}},
    "defaultContentItem": {
        "@name": "Breadcrumbs",
        "displayNamePropertyAlias": "displayName"
    },
    "locales": {}
}